.gitignore
AUTHORS.rst
LICENSE
MANIFEST.in
README.md
__init__.py
setup.py
pmstracks/__init__.py
pmstracks/_version.py
pmstracks/pmstracks.py
pmstracks.egg-info/PKG-INFO
pmstracks.egg-info/SOURCES.txt
pmstracks.egg-info/dependency_links.txt
pmstracks.egg-info/requires.txt
pmstracks.egg-info/top_level.txt
pmstracks/tracks/BCAH97/BCAH97_models
pmstracks/tracks/BCAH97/BCAH97_models.HSTflight
pmstracks/tracks/BCAH98/BCAH98_iso.1
pmstracks/tracks/BCAH98/BCAH98_iso.1HSTfilters
pmstracks/tracks/BCAH98/BCAH98_iso.2
pmstracks/tracks/BCAH98/BCAH98_iso.2HSTfilters
pmstracks/tracks/BCAH98/BCAH98_iso.3
pmstracks/tracks/BCAH98/BCAH98_iso.3HSTfilters
pmstracks/tracks/BCAH98/BCAH98_iso.3_extend
pmstracks/tracks/BCAH98/BCAH98_iso.mh05
pmstracks/tracks/BCAH98/BCAH98_models.1
pmstracks/tracks/BCAH98/BCAH98_models.2
pmstracks/tracks/BCAH98/BCAH98_models.3
pmstracks/tracks/BCAH98/BCAH98_models.3_extend
pmstracks/tracks/BCAH98/BCAH98_models.mh05
pmstracks/tracks/BCAH98/BCAH98_models.mh05HSTfilters
pmstracks/tracks/BHAC15/BHAC15_iso.2mass
pmstracks/tracks/BHAC15/BHAC15_iso.CFHT
pmstracks/tracks/BHAC15/BHAC15_iso.CIT2
pmstracks/tracks/BHAC15/BHAC15_iso.JWST
pmstracks/tracks/BHAC15/BHAC15_iso.SPHERE
pmstracks/tracks/BHAC15/BHAC15_iso.SPITZER
pmstracks/tracks/BHAC15/BHAC15_iso.ukidss
pmstracks/tracks/BHAC15/BHAC15_tracks.dat
pmstracks/tracks/BHAC15/BHAC15_tracks_structure
pmstracks/tracks/BHAC15/READ_INFO
pmstracks/tracks/COND03/COND03_models
pmstracks/tracks/DUSTY00/DUSTY00_models
pmstracks/tracks/DUSTY00/DUSTY00_models.HSTfilters
pmstracks/tracks/F16_mag/m0085_GS98_p000_p0_y28_mlt1.884_mag27kG.ntrk
pmstracks/tracks/F16_mag/m0090_GS98_p000_p0_y28_mlt1.884_mag27kG.ntrk
pmstracks/tracks/F16_mag/m0100_GS98_p000_p0_y28_mlt1.884_mag26kG.ntrk
pmstracks/tracks/F16_mag/m0120_GS98_p000_p0_y28_mlt1.884_mag26kG.ntrk
pmstracks/tracks/F16_mag/m0140_GS98_p000_p0_y28_mlt1.884_mag26kG.ntrk
pmstracks/tracks/F16_mag/m0160_GS98_p000_p0_y28_mlt1.884_mag26kG.ntrk
pmstracks/tracks/F16_mag/m0240_GS98_p000_p0_y28_mlt1.884_mag25kG.ntrk
pmstracks/tracks/F16_mag/m0260_GS98_p000_p0_y28_mlt1.884_mag25kG.ntrk
pmstracks/tracks/F16_mag/m0280_GS98_p000_p0_y28_mlt1.884_mag25kG.ntrk
